<?xml version='1.0' encoding='utf-8'?>
<song number="200" name="Когда трудно тебе, о дитя, на путях твоих," canon="false" text="Т. Витман" textRus="" music="Т. Витман" additionalInfo="">
    <verse number="1">
        <string>
            <plain>Когда трудно тебе, о дитя, на путях твоих,</plain>
        </string>
        <string>
            <plain>Не забудь, что с тобой всегда рядом Я.</plain>
        </string>
        <string>
            <plain>Рядом Я, когда слезы застыли в глазах твоих,</plain>
        </string>
        <string>
            <plain>Когда боль непосильная мучит тебя.</plain>
        </string>
    </verse>
    <verse number="2">
        <string>
            <plain>Ты не верь, когда враг сеет в сердце сомнения,</plain>
        </string>
        <string>
            <plain>В этот миг ты на Крест Мой голгофский взгляни.</plain>
        </string>
        <string>
            <plain>Разве мог кто пойти на такие мученья,</plain>
        </string>
        <string>
            <plain>Не имея великой, безмерной любви?</plain>
        </string>
    </verse>
    <verse number="3">
        <string>
            <plain>Та Любовь понесла за тебя все страдания</plain>
        </string>
        <string>
            <plain>И грехи Своей кровью омыла твои,</plain>
        </string>
        <string>
            <plain>Чтобы мог ты пройти все свои испытания,</plain>
        </string>
        <string>
            <plain>Доверяя всецело себя той Любви.</plain>
        </string>
    </verse>
    <verse number="4">
        <string>
            <plain>Нет того, кто утешит тебя в дни страдания,</plain>
        </string>
        <string>
            <plain>Нет того, кто склонится, как мать, над тобой.</plain>
        </string>
        <string>
            <plain>В дни, когда так горьки все твои испытания,</plain>
        </string>
        <string>
            <plain>Знай, что взор Мой отцовский всегда над тобой.</plain>
        </string>
    </verse>
    <verse number="5">
        <string>
            <plain>Ты поверь, что нельзя по-другому пройти тебе.</plain>
        </string>
        <string>
            <plain>Знаю Я, что так нужно сейчас для тебя,</plain>
        </string>
        <string>
            <plain>Чтоб потом пред тобою открыл рая двери Я</plain>
        </string>
        <string>
            <plain>И сказал: «Ты войди в Мою радость, дитя».</plain>
        </string>
    </verse>
    <verse number="6">
        <string>
            <plain>И когда оборвутся земные пути твои,</plain>
        </string>
        <string>
            <plain>Позову тебя в дом твой родной – в Небеса.</plain>
        </string>
        <string>
            <plain>Я пронзенной рукой сотру слезы с очей твоих,</plain>
        </string>
        <string>
            <plain>И тогда ты поймешь, для чего ты страдал.</plain>
        </string>
    </verse>
    <verse number="0">
        <string>
            <plain>Ты увидишь, как Я оценил слезы все твои,</plain>
        </string>
        <string>
            <plain>И поймешь, что не зря на земле ты страдал.</plain>
        </string>
    </verse>
</song>