<?xml version='1.0' encoding='utf-8'?>
<song number="125" name="Земля трепещет и сверкая" canon="false" text="" textRus="" music="">
    <verse number="1">
        <string>
            <plain>Земля трепещет и, сверкая,</plain>
        </string>
        <string>
            <plain>Катится гром из края в край:</plain>
        </string>
        <string>
            <plain>То Божий глас гремит, взывая:</plain>
        </string>
        <string>
            <plain>"Израиль, мой народ, внимай!</plain>
        </string>
    </verse>
    <verse number="2">
        <string>
            <plain>Израиль! Ты Мне строишь храмы,</plain>
        </string>
        <string>
            <plain>И храмы золотом блестят,</plain>
        </string>
        <string>
            <plain>И в них курятся фимиамы,</plain>
        </string>
        <string>
            <plain>И день и ночь они горят.</plain>
        </string>
    </verse>
    <verse number="3">
        <string>
            <plain>К чему Мне ваших храмов своды,</plain>
        </string>
        <string>
            <plain>Бездушный камень, прах земной?</plain>
        </string>
        <string>
            <plain>Я создал землю, создал воды</plain>
        </string>
        <string>
            <plain>И небо очертил рукой.</plain>
        </string>
    </verse>
    <verse number="4">
        <string>
            <plain>К чему Мне злато? В глубь земную,</plain>
        </string>
        <string>
            <plain>В утробу вековечных скал</plain>
        </string>
        <string>
            <plain>Я влил, как воду дождевую,</plain>
        </string>
        <string>
            <plain>Огнем расплавленный металл.</plain>
        </string>
    </verse>
    <verse number="5">
        <string>
            <plain>К чему куренья? Предо Мною</plain>
        </string>
        <string>
            <plain>Земля со всех своих концов</plain>
        </string>
        <string>
            <plain>Кадит дыханьем под росою</plain>
        </string>
        <string>
            <plain>Благоухающих цветов.</plain>
        </string>
    </verse>
    <verse number="6">
        <string>
            <plain>К чему огни? Не Я ль светила</plain>
        </string>
        <string>
            <plain>Зажег над вашей головой?</plain>
        </string>
        <string>
            <plain>Не Я ль, как искры из горнила,</plain>
        </string>
        <string>
            <plain>Бросаю звезды в мрак ночной?</plain>
        </string>
    </verse>
    <verse number="7">
        <string>
            <plain>Твой скуден дар. Есть дар бесценный,</plain>
        </string>
        <string>
            <plain>Дар нужный Богу твоему;</plain>
        </string>
        <string>
            <plain>Ты с ним явись, и примиренный</plain>
        </string>
        <string>
            <plain>Я все дары твои приму.</plain>
        </string>
    </verse>
    <verse number="8">
        <string>
            <plain>Мне нужно сердце чище злата</plain>
        </string>
        <string>
            <plain>И воля крепкая в труде,</plain>
        </string>
        <string>
            <plain>Мне нужен брат, любящий брата</plain>
        </string>
        <string>
            <plain>И верный Мне всегда, везде".</plain>
        </string>
    </verse>
</song>