<?xml version='1.0' encoding='utf-8'?>
<song number="1339" name="Пред Спасителем у ног Его святых" canon="false" text="" textRus="" music="">
    <verse number="1">
        <string>
            <plain>Пред Спасителем, у ног Его святых.</plain>
        </string>
        <string>
            <plain>Слушала Мария звуки слов живых;</plain>
        </string>
        <string>
            <plain>Жаждала она принять От Иисуса благодать.</plain>
        </string>
        <string>
            <plain>Пред Спасителем у ног и я готов</plain>
        </string>
        <string>
            <plain>Вечно пребывать при звуках дивных слов.</plain>
        </string>
    </verse>
    <verse number="2">
        <string>
            <plain>Быв у ног Иисуса, по любви своей.</plain>
        </string>
        <string>
            <plain>Возлила Мария на Него елей;</plain>
        </string>
        <string>
            <plain>За любовь в утеху слез Ей простил грехи Христос.</plain>
        </string>
        <string>
            <plain>Пред Спасителем у ног и я слугой</plain>
        </string>
        <string>
            <plain>Верным быть желаю сердцем и душой.</plain>
        </string>
    </verse>
    <verse number="3">
        <string>
            <plain>Пав к ногам Христа, воскресшего зарей.</plain>
        </string>
        <string>
            <plain>Видела Мария лик Его святой;</plain>
        </string>
        <string>
            <plain>Прежде всех ее уста Возвестили мир Христа.</plain>
        </string>
        <string>
            <plain>Пред Спасителем у ног, как ученик.</plain>
        </string>
        <string>
            <plain>Жажду славить я Его, как Он велик!</plain>
        </string>
    </verse>
</song>