<?xml version='1.0' encoding='utf-8'?>
<song number="1870" name="Будь Спаситель с нами" canon="false" text="" textRus="" music="">
    <verse number="1">
        <string>
            <plain>Будь, Спаситель, с нами:</plain>
        </string>
        <string>
            <plain>Сердце возроди</plain>
        </string>
        <string>
            <plain>- Радости пламя</plain>
        </string>
        <string>
            <plain>Разожги в груди.</plain>
        </string>
        <string>
            <plain>Ты сделать можешь</plain>
        </string>
        <string>
            <plain>Чудо из чудес,</plain>
        </string>
        <string>
            <plain>Так сделай Боже,</plain>
        </string>
        <string>
            <plain>Чтобы я воскрес.</plain>
        </string>
    </verse>
    <chorus number="1">
        <string>
            <plain>Ключ каждой жизни</plain>
        </string>
        <string>
            <plain>И любви исток,</plain>
        </string>
        <string>
            <plain>Мой путь к отчизне,</plain>
        </string>
        <string>
            <plain>В край, где нет тревог,</plain>
        </string>
        <string>
            <plain>Мой дом, обитель,</plain>
        </string>
        <string>
            <plain>Там, в конце дорог,</plain>
        </string>
        <string>
            <plain>Иисус Спаситель,</plain>
        </string>
        <string>
            <plain>Мой Господь и Бог.</plain>
        </string>
    </chorus>
    <verse number="2">
        <string>
            <plain>Крест Твой и страданья</plain>
        </string>
        <string>
            <plain>- Это мне завет.</plain>
        </string>
        <string>
            <plain>Дай упованье</plain>
        </string>
        <string>
            <plain>- Веры яркий свет.</plain>
        </string>
        <string>
            <plain>Твой путь спасенье,</plain>
        </string>
        <string>
            <plain>Вечной жизни ключ.</plain>
        </string>
        <string>
            <plain>Дай мне терпенье</plain>
        </string>
        <string>
            <plain>И надежды луч.</plain>
        </string>
    </verse>
    <verse number="3">
        <string>
            <plain>Вот меня коснулась</plain>
        </string>
        <string>
            <plain>Божия ладонь</plain>
        </string>
        <string>
            <plain>- Сердце проснулось,</plain>
        </string>
        <string>
            <plain>И горит огонь.</plain>
        </string>
        <string>
            <plain>Вера пылает,</plain>
        </string>
        <string>
            <plain>Разум мой поет:</plain>
        </string>
        <string>
            <plain>Он точно знает</plain>
        </string>
        <string>
            <plain>- Наш Господь грядет!</plain>
        </string>
    </verse>
</song>