<?xml version='1.0' encoding='utf-8'?>
<song number="1876" name="Господь нам данное Тобой" canon="false" text="" textRus="" music="">
    <verse number="1">
        <string>
            <plain>Господь, нам данное Тобой</plain>
        </string>
        <string>
            <plain>Божественное слово -</plain>
        </string>
        <string>
            <plain>Источник чистый и святой</plain>
        </string>
        <string>
            <plain>Добра и жизни новой.</plain>
        </string>
        <string>
            <plain>Для нас оно Изречено Твоими,</plain>
        </string>
        <string>
            <plain>Бог, устами; И в полноте,</plain>
        </string>
        <string>
            <plain>И в чистоте Своей принято нами.</plain>
        </string>
    </verse>
    <verse number="2">
        <string>
            <plain>Хотя погибнет в мире все:</plain>
        </string>
        <string>
            <plain>Земля и строй вселенной,</plain>
        </string>
        <string>
            <plain>Но слово, Господи, Твое</plain>
        </string>
        <string>
            <plain>Пребудет неизменно.</plain>
        </string>
        <string>
            <plain>Ни мира тьма, Ни власть ума</plain>
        </string>
        <string>
            <plain>Его не уничтожит,</plain>
        </string>
        <string>
            <plain>И благо всем. Кто словом тем</plain>
        </string>
        <string>
            <plain>Жить в мире этом может.</plain>
        </string>
    </verse>
    <verse number="3">
        <string>
            <plain>Твое святое слово нам</plain>
        </string>
        <string>
            <plain>Спасенье возвещает</plain>
        </string>
        <string>
            <plain>И утомленным всем сердцам</plain>
        </string>
        <string>
            <plain>Отраду обещает.</plain>
        </string>
        <string>
            <plain>В нем жизнь для нас</plain>
        </string>
        <string>
            <plain>Во всякий час До смерти, до могилы;</plain>
        </string>
        <string>
            <plain>Любви завет, Надежды свет</plain>
        </string>
        <string>
            <plain>И веры нашей сила.</plain>
        </string>
    </verse>
    <verse number="4">
        <string>
            <plain>Когда мы скорби крест несем,</plain>
        </string>
        <string>
            <plain>- Оно нас утешает;</plain>
        </string>
        <string>
            <plain>Когда мы духом упадем,</plain>
        </string>
        <string>
            <plain>- В нас силу обновляет.</plain>
        </string>
        <string>
            <plain>Христос во всем Снимает грех</plain>
        </string>
        <string>
            <plain>И страх, и все мученья.</plain>
        </string>
        <string>
            <plain>Мы за Христом В Отцовский дом</plain>
        </string>
        <string>
            <plain>Идем чрез искушенья.</plain>
        </string>
    </verse>
    <verse number="5">
        <string>
            <plain>Нас навсегда вооружи</plain>
        </string>
        <string>
            <plain>Твоим могучим словом,</plain>
        </string>
        <string>
            <plain>Чтоб в буре царствующей лжи</plain>
        </string>
        <string>
            <plain>Быть под его покровом.</plain>
        </string>
        <string>
            <plain>Да будет им Наш дух храним</plain>
        </string>
        <string>
            <plain>От страха и неверья!</plain>
        </string>
        <string>
            <plain>Пусть в нас Он Сам устроит храм</plain>
        </string>
        <string>
            <plain>Любви без лицемерья.</plain>
        </string>
    </verse>
</song>