<?xml version='1.0' encoding='utf-8'?>
<song number="2150" name="Наши годы кратки Наши дни мелькают" canon="false" text="" textRus="" music="">
    <verse number="1">
        <string>
            <plain>Наши годы кратки, Наши дни мелькают,</plain>
        </string>
        <string>
            <plain>Как мелькают в небе Быстрые стрижи,</plain>
        </string>
        <string>
            <plain>А слова Писаны Нам напоминают:</plain>
        </string>
        <string>
            <plain>Все во имя Бога Делай от души.</plain>
        </string>
    </verse>
    <verse number="2">
        <string>
            <plain>Иисус зовет Не кое-как работать.</plain>
        </string>
        <string>
            <plain>Сей со всем усердьем, Молоти, паши.</plain>
        </string>
        <string>
            <plain>В церкви труд священный Не оброк, не подать,</plain>
        </string>
        <string>
            <plain>- Это добровольная Служба от души.</plain>
        </string>
    </verse>
    <verse number="3">
        <string>
            <plain>Прихоти плотские Могут стоить сотни,</plain>
        </string>
        <string>
            <plain>На тарелку Божью Можно класть гроши.</plain>
        </string>
        <string>
            <plain>Правильно используй Все дары Господин,</plain>
        </string>
        <string>
            <plain>И на дело Божье Жертвуй от души.</plain>
        </string>
    </verse>
    <verse number="4">
        <string>
            <plain>Сознавать приятно, Что ты людям нужен,</plain>
        </string>
        <string>
            <plain>Что тобой, как другом, Кто-то дорожит,</plain>
        </string>
        <string>
            <plain>Значит, будь отзывчив, Чуток, добродушен,</plain>
        </string>
        <string>
            <plain>Все во имя Бога Делай от души.</plain>
        </string>
    </verse>
</song>