<?xml version='1.0' encoding='utf-8'?>
<song number="2265" name="О светлый образ радость благодатная" canon="false" text="" textRus="" music="">
    <verse number="1">
        <string>
            <plain>О светлый образ, радость благодатная,</plain>
        </string>
        <string>
            <plain>Иисус Христос - спасение души</plain>
        </string>
        <string>
            <plain>Любовь Твоя такая непонятная,</plain>
        </string>
        <string>
            <plain>Она сильнее зла и больше тьмы.</plain>
        </string>
    </verse>
    <verse number="2">
        <string>
            <plain>Я без Тебя дорогами неверными</plain>
        </string>
        <string>
            <plain>Шел долго, долго, плача и греша.</plain>
        </string>
        <string>
            <plain>Людей и жизнь назвал я скверными,</plain>
        </string>
        <string>
            <plain>И не хотел я знать и звать Тебя.</plain>
        </string>
    </verse>
    <verse number="3">
        <string>
            <plain>Не знал того, что нет границ прощения,</plain>
        </string>
        <string>
            <plain>И нет границ любви Твоей ко мне,</plain>
        </string>
        <string>
            <plain>Но ждал я от Тебя лишь только мщения</plain>
        </string>
        <string>
            <plain>За зло души, погрязшей в вечной тьме.</plain>
        </string>
    </verse>
    <verse number="4">
        <string>
            <plain>Прости меня, прости, Владыка мира,</plain>
        </string>
        <string>
            <plain>Даруй мне разум, радость и любовь.</plain>
        </string>
        <string>
            <plain>Прости меня, Спаситель, Свет незримый,</plain>
        </string>
        <string>
            <plain>Прости за все, я повторяю вновь.</plain>
        </string>
    </verse>
</song>