<?xml version='1.0' encoding='utf-8'?>
<song number="2756" name="Пораньше встань на солнце взглянь" canon="false" text="" textRus="" music="">
    <verse number="1">
        <string>
            <plain>Пораньше встань, на солнце взглянь,</plain>
        </string>
        <string>
            <plain>В небе будет отдых скоро,</plain>
        </string>
        <string>
            <plain>Труд скорей свершай.</plain>
        </string>
        <string>
            <plain>Могу ли огорчать Иисуса Христа?</plain>
        </string>
    </verse>
    <chorus number="1">
        <string>
            <plain>Могу ли огорчать,</plain>
        </string>
        <string>
            <plain>моту ли огорчать,</plain>
        </string>
        <string>
            <plain>Иисуса Христа?</plain>
        </string>
    </chorus>
    <verse number="2">
        <string>
            <plain>О мне суди, как хочешь Ты,</plain>
        </string>
        <string>
            <plain>А теперь готовься Богу</plain>
        </string>
        <string>
            <plain>Лишь сказать: прости.</plain>
        </string>
        <string>
            <plain>Могу ли огорчать Иисуса Христа?</plain>
        </string>
    </verse>
    <verse number="3">
        <string>
            <plain>Когда придет день светлый тот,</plain>
        </string>
        <string>
            <plain>Сам Христос. придет на землю,</plain>
        </string>
        <string>
            <plain>Нас к Себе возьмет.</plain>
        </string>
        <string>
            <plain>Могу ли огорчать Иисуса Христа?</plain>
        </string>
    </verse>
    <verse number="4">
        <string>
            <plain>Увижу ль я святой Сион,</plain>
        </string>
        <string>
            <plain>Песни славы там блаженны,</plain>
        </string>
        <string>
            <plain>Полон счастья он.</plain>
        </string>
        <string>
            <plain>Могу ли огорчать Иисуса Христа?</plain>
        </string>
    </verse>
    <verse number="5">
        <string>
            <plain>Настал для нас проверки час,</plain>
        </string>
        <string>
            <plain>На Иисуса лишь взирая,</plain>
        </string>
        <string>
            <plain>Устоим в тот час.</plain>
        </string>
        <string>
            <plain>Могу ли огорчать Иисуса Христа?</plain>
        </string>
    </verse>
</song>