<?xml version='1.0' encoding='utf-8'?>
<song number="2961" name="Когда придет не знаю мой смертный час" canon="false" text="" textRus="" music="">
    <verse number="1">
        <string>
            <plain>Когда придет, не знаю, мой смертный час,</plain>
        </string>
        <string>
            <plain>но Библия нас учит чтить Господа наказ,</plain>
        </string>
        <string>
            <plain>светить подобно солнцу огнем святым,</plain>
        </string>
        <string>
            <plain>чтоб в день, когда придет Он душа могла быть с Ним.</plain>
        </string>
    </verse>
    <chorus number="1">
        <string>
            <plain>Господь один лишь знает мой смертный час,</plain>
        </string>
        <string>
            <plain>- ничто не разделяет отныне с Богом нас.</plain>
        </string>
    </chorus>
    <verse number="2">
        <string>
            <plain>Хочу всегда я помнить про смертный час;</plain>
        </string>
        <string>
            <plain>хочу остаться верным Христу я и в скорбях,</plain>
        </string>
        <string>
            <plain>служить Ему все сердцем свой крест неся;</plain>
        </string>
        <string>
            <plain>тогда в день воскресенья Он наградит меня.</plain>
        </string>
    </verse>
    <verse number="3">
        <string>
            <plain>Быть может уже близок мой смертный час;</plain>
        </string>
        <string>
            <plain>ему я рад и в мыслях предвижу уж сейчас.</plain>
        </string>
        <string>
            <plain>Мне град небесный виден уж издали,</plain>
        </string>
        <string>
            <plain>и ангелы святые поют там песнь хвалы.</plain>
        </string>
    </verse>
</song>