<?xml version='1.0' encoding='utf-8'?>
<song number="846" name="Вдоль по миру счастье проходит" canon="false" text="" textRus="" music="">
    <verse number="1">
        <string>
            <plain>Вдоль по миру счастье проходит,</plain>
        </string>
        <string>
            <plain>А в мире так скучно, темно.</plain>
        </string>
        <string>
            <plain>И в каждую дверь мимоходом.</plain>
        </string>
        <string>
            <plain>Хоть слабо, да стукнет оно.</plain>
        </string>
    </verse>
    <verse number="2">
        <string>
            <plain>И к тем, кто живет беззаботно,</plain>
        </string>
        <string>
            <plain>И к тем, кто печалью</plain>
        </string>
        <string>
            <plain>убит, В блестящие замка ворота</plain>
        </string>
        <string>
            <plain>И к нищему в двери стучит.</plain>
        </string>
    </verse>
    <verse number="3">
        <string>
            <plain>Но люди и слепы, и глухи,</plain>
        </string>
        <string>
            <plain>Заняты мирской суетой,</plain>
        </string>
        <string>
            <plain>К познаниям истины пути.</plain>
        </string>
        <string>
            <plain>Пленены житейской враждой.</plain>
        </string>
    </verse>
    <verse number="4">
        <string>
            <plain>Их манят далекие грёзы.</plain>
        </string>
        <string>
            <plain>Терзает вседневное зло.</plain>
        </string>
        <string>
            <plain>В тоске и печали льют слезы:</plain>
        </string>
        <string>
            <plain>О где же ты, счастье мое?</plain>
        </string>
    </verse>
    <verse number="5">
        <string>
            <plain>Но лик их ненавистью дышит,</plain>
        </string>
        <string>
            <plain>Свое проклинают бытье,</plain>
        </string>
        <string>
            <plain>И ропщут, и счастия ищут,</plain>
        </string>
        <string>
            <plain>А счастье уж дальше ушло.</plain>
        </string>
    </verse>
    <verse number="6">
        <string>
            <plain>Но где будет счастье без Бога?</plain>
        </string>
        <string>
            <plain>Здесь в мире его не найдешь.</plain>
        </string>
        <string>
            <plain>Здесь скорби, борьба и тревога,</plain>
        </string>
        <string>
            <plain>А счастье дает лишь Христос.</plain>
        </string>
    </verse>
    <verse number="7">
        <string>
            <plain>Проверь же себя, друг, сегодня,</plain>
        </string>
        <string>
            <plain>Нашел ли ты счастье свое,</plain>
        </string>
        <string>
            <plain>Любовь, что есть милость Господня,</plain>
        </string>
        <string>
            <plain>Блаженство в Иисусе Христе?</plain>
        </string>
    </verse>
</song>