<?xml version='1.0' encoding='utf-8'?>
<song number="856" name="Во дни прекрасной юности не знал я суеты" canon="false" text="" textRus="" music="">
    <verse number="1">
        <string>
            <plain>Во дни прекрасной юности не знал я суеты.</plain>
        </string>
        <string>
            <plain>Не знал забот, Не знал хлопот с утра и до зари,</plain>
        </string>
        <string>
            <plain>Ни о чем я не заботился, по воле своей жил,</plain>
        </string>
        <string>
            <plain>А скорбь о мне сжимала грудь у матери моей.</plain>
        </string>
    </verse>
    <chorus number="1">
        <string>
            <plain>В молитве матери.</plain>
        </string>
        <string>
            <plain>В молитве матери.</plain>
        </string>
        <string>
            <plain>Я имя услыхал свое,</plain>
        </string>
        <string>
            <plain>В молитве матери.</plain>
        </string>
    </chorus>
    <verse number="2">
        <string>
            <plain>Ходил путями помыслов, о Боге не мечтал</plain>
        </string>
        <string>
            <plain>- Своей любимой матери тем скорби причинял.</plain>
        </string>
        <string>
            <plain>Но сердце в ней любимое молилось в эти дни,</plain>
        </string>
        <string>
            <plain>И слышал имя я свое в молитве матери.</plain>
        </string>
    </verse>
    <verse number="3">
        <string>
            <plain>В часы моих веселых дней звучал мне глас любви:</plain>
        </string>
        <string>
            <plain>"Смотри, сын мой, не забывай молитву матери,</plain>
        </string>
        <string>
            <plain>Беги греха, не делай зла, храни себя, храни!"</plain>
        </string>
        <string>
            <plain>Вновь слышал имя я мое в молитве матери.</plain>
        </string>
    </verse>
    <verse number="4">
        <string>
            <plain>То сердце, полное любви, почило уж давно,</plain>
        </string>
        <string>
            <plain>А глас ее в душе моей твердит мне об одном:</plain>
        </string>
        <string>
            <plain>"Беги греха, не делай зла и с Господом живи!"</plain>
        </string>
        <string>
            <plain>И слышу имя я свое в молитве матери.</plain>
        </string>
    </verse>
    <verse number="5">
        <string>
            <plain>Теперь нашел я у Христа спасенье для души.</plain>
        </string>
        <string>
            <plain>Сложил грехи у ног Христа, молясь Ему в тиши.</plain>
        </string>
        <string>
            <plain>И счастие спасения, и луч святой зари</plain>
        </string>
        <string>
            <plain>Пролил Христос на разум мой молитвой матери.</plain>
        </string>
    </verse>
</song>